bloques_codigo/Codigos/ffd.vhd
-- Flip - Flop D con enable y reset
-- Estudiante: Fernandez, Rocio
library IEEE;
use IEEE.std_logic_1164.all;

entity ffd is
	port (
		clk_i : in std_logic; -- Clock
		rst_i : in std_logic; -- Reset
		ena_i : in std_logic; -- Enable
		d_i   : in std_logic; -- Dato
		q_o   : out std_logic -- Salida
	);
end entity;

architecture ffd_arc of ffd is
begin
	process(clk_i)
	begin
		if rising_edge(clk_i) then 
			if rst_i = '1' then         -- Reset activo
				q_o <= '0';
			elsif ena_i = '1' then      -- Enable activo
				q_o <= d_i;
			end if;
		end if;
	end process;
end architecture;

bloques_codigo/Codigos/comp_Nb.vhd
-- Comparador de N bits
-- Estudiante: Fernandez, Rocio


entity comp_Nb is
  generic(N: natural := 10);
  port(
    a: in  bit_vector(N-1 downto 0);  --  A
    b: in  bit_vector(N-1 downto 0);  -- B
    s: out bit                       -- Salida: '1' si A = B
  );
end;

architecture comp_Nb_arq of comp_Nb is
  signal xnor_aux: bit_vector(N-1 downto 0);
  signal and_aux:  bit_vector(N-1 downto 0);
begin

  -- Compara bit a bit usando XNOR
  gen_xnor: for i in 0 to N-1 generate
    xnor_aux(i) <= a(i) xnor b(i);
  end generate;

  -- And de todos los bits (en cascada)
  and_aux(0) <= xnor_aux(0);
  gen_and: for i in 1 to N-1 generate
    and_aux(i) <= and_aux(i-1) and xnor_aux(i);
  end generate;

  -- Salida: '1' si todos los bits coinciden
  s <= and_aux(N-1);

end architecture;

bloques_codigo/Codigos/cont_bin_gen.vhd
-- CONTADOR BINARIO DE 16 bits


entity cont_bin_gen is
  generic(
      N: natural := 4 
  );
  port (
    clk_bin_gen : in bit;
    ena_bin_gen : in bit;
    rst_bin_gen : in bit;
    salida_gen  : out bit_vector(N-1 downto 0)
  );
end entity;

architecture cont_bin_gen_arq of cont_bin_gen is

  component ffd is
    port (
      clk_i   : in  bit;
      rst_i   : in  bit;
      ena_i   : in  bit;
      d_i     : in  bit;
      q_o     : out bit
    );
  end component;

    signal salAnd   : bit_vector(N-1 downto 0);  
    signal salXor   : bit_vector(N-1 downto 0); 
    -- signal entrada  : bit_vector(9 downto 0);
    signal salida   : bit_vector(N-1 downto 0);

begin
    salAnd(0) <= ena_bin_gen;
    salXor(0) <= salAnd(0) xor salida(0);

    cont_bin10: for i in 0 to N-1 generate
        etapa_0: if i = 0 generate
            ffd0: ffd port map (
                        clk_i => clk_bin_gen,
                        rst_i => rst_bin_gen,
                        ena_i => '1',
                        d_i => salXor(0),
                        q_o => salida(0)
                    );
        end generate;
        
        etapa_1: if i > 0 generate
            --conexiones de las N etapas
            salAnd(i) <= salAnd(i-1) and salida(i-1);
            salXor(i) <= salAnd(i) xor salida(i);

            ffdN: ffd port map (
                        clk_i => clk_bin_gen,
                        rst_i => rst_bin_gen,
                        ena_i => '1',
                        d_i => salXor(i),
                        q_o => salida(i)
                    );
        end generate;
    end generate;
    
    salida_gen <= salida;
end;

bloques_codigo/Codigos/hsync.vhd
-- sincronismo horizontal 

entity hsync is 
    port (
        ena_hsync   : in bit;
        rst_hsync   : in bit;
        clk_hsync   : in bit;
        h_sync      : out bit;
        h_vidon     : out bit;
        ena_cv      : out bit;
        cont_h      : out bit_vector(9 downto 0)
    );

end; 

architecture hsync_arq of hsync is 

    -- contador binario, necesito que cuente hasta 800 --> 10 bits
    component cont_bin_gen is 
        generic(
            N: natural := 10 
        );
        port (
            clk_bin_gen : in bit;
            ena_bin_gen : in bit;
            rst_bin_gen : in bit;
            salida_gen  : out bit_vector(N-1 downto 0)
        );
    end component;

    component  comp_Nb is
        port ( 
            a       : in bit_vector(9 downto 0);
            b       : in bit_vector(9 downto 0);
            s  : out bit
        );
    end component;

    component ffd is 
        port(
            clk_i   : in bit;
            rst_i   : in bit;
            ena_i   : in bit;
            d_i     : in bit;
            q_o     : out bit
        );
    end component;

    signal cuenta       : bit_vector(9 downto 0) := (9 downto 0 => '0');
    signal reset_aux    : bit := '0';
    signal comp_639     : bit := '0';   -- 1001111111
    signal comp_655     : bit := '0';   -- 1010001111
    signal comp_751     : bit := '0';   -- 1011101111
    signal comp_799     : bit := '0';   -- 1100011111
    signal sal_hsync    : bit := '0';
    signal sal_hvidon   : bit := '0';

begin

    -- contador hasta 800 = 1100100000
    cont800: cont_bin_gen
        port map (
            clk_bin_gen => clk_hsync,
            ena_bin_gen => ena_hsync,
            rst_bin_gen => reset_aux,
            salida_gen  => cuenta           
        );

    -- comparadores 

    comp639: comp_Nb 
        port map(
            a       => cuenta,
            b       => "1001111111",
            s  =>  comp_639
        );

    comp655: comp_Nb 
        port map(
            a       => cuenta,
            b       => "1010001111",
            s  =>  comp_655
        );
        
    comp751: comp_Nb 
        port map(
            a       => cuenta,
            b       => "1011101111",
            s  => comp_751
        );
        
    comp799: comp_Nb 
        port map(
            a       => cuenta,
            b       => "1100011111",
            s  => comp_799
        );
    
    -- necesito 2 ffd para negar las salidas y asi generar los pulsos 

    ffdhsync: ffd
        port map(
            clk_i   => clk_hsync,
            rst_i   => comp_751,
            ena_i   => comp_655,
            d_i     => '1',
            q_o     => sal_hsync
        );

    ffdhvidon: ffd
        port map(
            clk_i   => clk_hsync,
            rst_i   => comp_799,
            ena_i   => comp_639,
            d_i     => '1',
            q_o     => sal_hvidon
        );

    h_sync       <= not sal_hsync;           -- niego la salida del ffd y sale
    h_vidon      <= not sal_hvidon;          -- niego la salida del ffd y sale
    ena_cv      <= comp_799;                -- cuando el contador llega a 799 habilita al contador vertical
    cont_h      <= cuenta;                  -- saco la salida del contador
    -- el contador horiz se resetea por rst del sistema o por fin de cuenta 799 = 1100011111
    reset_aux   <= rst_hsync or comp_799;   
end;

bloques_codigo/Codigos/hsync/Fuentes/hsync_tb.vhd
-- Test sincronismo horizontal

entity hsync_tb is 
end;

architecture hsync_tb_arq of hsync_tb is 

    component hsync is 
        port (
            ena_hsync   : in bit;
            rst_hsync   : in bit;
            clk_hsync   : in bit;
            h_sync      : out bit;
            h_vidon     : out bit;
            ena_cv      : out bit;
            cont_h      : out bit_vector(9 downto 0)
        );
    
    end component;

    
    signal ena_hsync_tb   : bit := '0';
    signal rst_hsync_tb   : bit := '0';
    signal clk_hsync_tb   : bit := '0';
    signal h_sync_tb      : bit := '0';
    signal h_vidon_tb     : bit := '0';
    signal ena_cv_tb      : bit := '0';
    signal cont_h_tb      : bit_vector(9 downto 0) := (9 downto 0 => '0');

begin

    ena_hsync_tb <= '1' after 10 ns;
    clk_hsync_tb <= not clk_hsync_tb after 20 ns;
    -- rst_hsync_tb <= '1' after 30 ns, '0' after 40 ns;

    DUT: hsync
        port map(
            ena_hsync   => ena_hsync_tb,
            rst_hsync   => rst_hsync_tb,
            clk_hsync   => clk_hsync_tb,
            h_sync      => h_sync_tb,
            h_vidon     => h_vidon_tb,
            ena_cv      => ena_cv_tb,
            cont_h      => cont_h_tb
        );
end;

bloques_codigo/Codigos/hsync/Simulacion/hsync_tb.vcd
$date
  Thu Jul 17 11:22:45 2025
$end
$version
  GHDL v0
$end
$timescale
  1 fs
$end
$scope module standard $end
$upscope $end
$scope module hsync_tb $end
$var reg 1 ! ena_hsync_tb $end
$var reg 1 " rst_hsync_tb $end
$var reg 1 # clk_hsync_tb $end
$var reg 1 $ h_sync_tb $end
$var reg 1 % h_vidon_tb $end
$var reg 1 & ena_cv_tb $end
$var reg 10 ' cont_h_tb[9:0] $end
$scope module dut $end
$var reg 1 ( ena_hsync $end
$var reg 1 ) rst_hsync $end
$var reg 1 * clk_hsync $end
$var reg 1 + h_sync $end
$var reg 1 , h_vidon $end
$var reg 1 - ena_cv $end
$var reg 10 . cont_h[9:0] $end
$var reg 10 / cuenta[9:0] $end
$var reg 1 0 reset_aux $end
$var reg 1 1 comp_639 $end
$var reg 1 2 comp_655 $end
$var reg 1 3 comp_751 $end
$var reg 1 4 comp_799 $end
$var reg 1 5 sal_hsync $end
$var reg 1 6 sal_hvidon $end
$scope module cont800 $end
$var reg 1 7 clk_bin_gen $end
$var reg 1 8 ena_bin_gen $end
$var reg 1 9 rst_bin_gen $end
$var reg 10 : salida_gen[9:0] $end
$var reg 10 ; saland[9:0] $end
$var reg 10 < salxor[9:0] $end
$var reg 10 = salida[9:0] $end
$scope module cont_bin10(0) $end
$scope module etapa_0 $end
$scope module ffd0 $end
$var reg 1 > clk_i $end
$var reg 1 ? rst_i $end
$var reg 1 @ ena_i $end
$var reg 1 A d_i $end
$var reg 1 B q_o $end
$upscope $end
$upscope $end
$upscope $end
$scope module cont_bin10(1) $end
$scope module etapa_1 $end
$scope module ffdn $end
$var reg 1 C clk_i $end
$var reg 1 D rst_i $end
$var reg 1 E ena_i $end
$var reg 1 F d_i $end
$var reg 1 G q_o $end
$upscope $end
$upscope $end
$upscope $end
$scope module cont_bin10(2) $end
$scope module etapa_1 $end
$scope module ffdn $end
$var reg 1 H clk_i $end
$var reg 1 I rst_i $end
$var reg 1 J ena_i $end
$var reg 1 K d_i $end
$var reg 1 L q_o $end
$upscope $end
$upscope $end
$upscope $end
$scope module cont_bin10(3) $end
$scope module etapa_1 $end
$scope module ffdn $end
$var reg 1 M clk_i $end
$var reg 1 N rst_i $end
$var reg 1 O ena_i $end
$var reg 1 P d_i $end
$var reg 1 Q q_o $end
$upscope $end
$upscope $end
$upscope $end
$scope module cont_bin10(4) $end
$scope module etapa_1 $end
$scope module ffdn $end
$var reg 1 R clk_i $end
$var reg 1 S rst_i $end
$var reg 1 T ena_i $end
$var reg 1 U d_i $end
$var reg 1 V q_o $end
$upscope $end
$upscope $end
$upscope $end
$scope module cont_bin10(5) $end
$scope module etapa_1 $end
$scope module ffdn $end
$var reg 1 W clk_i $end
$var reg 1 X rst_i $end
$var reg 1 Y ena_i $end
$var reg 1 Z d_i $end
$var reg 1 [ q_o $end
$upscope $end
$upscope $end
$upscope $end
$scope module cont_bin10(6) $end
$scope module etapa_1 $end
$scope module ffdn $end
$var reg 1 \ clk_i $end
$var reg 1 ] rst_i $end
$var reg 1 ^ ena_i $end
$var reg 1 _ d_i $end
$var reg 1 ` q_o $end
$upscope $end
$upscope $end
$upscope $end
$scope module cont_bin10(7) $end
$scope module etapa_1 $end
$scope module ffdn $end
$var reg 1 a clk_i $end
$var reg 1 b rst_i $end
$var reg 1 c ena_i $end
$var reg 1 d d_i $end
$var reg 1 e q_o $end
$upscope $end
$upscope $end
$upscope $end
$scope module cont_bin10(8) $end
$scope module etapa_1 $end
$scope module ffdn $end
$var reg 1 f clk_i $end
$var reg 1 g rst_i $end
$var reg 1 h ena_i $end
$var reg 1 i d_i $end
$var reg 1 j q_o $end
$upscope $end
$upscope $end
$upscope $end
$scope module cont_bin10(9) $end
$scope module etapa_1 $end
$scope module ffdn $end
$var reg 1 k clk_i $end
$var reg 1 l rst_i $end
$var reg 1 m ena_i $end
$var reg 1 n d_i $end
$var reg 1 o q_o $end
$upscope $end
$upscope $end
$upscope $end
$upscope $end
$scope module comp639 $end
$var reg 10 p a[9:0] $end
$var reg 10 q b[9:0] $end
$var reg 1 r s $end
$var reg 10 s xnor_aux[9:0] $end
$var reg 10 t and_aux[9:0] $end
$scope module gen_xnor(0) $end
$upscope $end
$scope module gen_xnor(1) $end
$upscope $end
$scope module gen_xnor(2) $end
$upscope $end
$scope module gen_xnor(3) $end
$upscope $end
$scope module gen_xnor(4) $end
$upscope $end
$scope module gen_xnor(5) $end
$upscope $end
$scope module gen_xnor(6) $end
$upscope $end
$scope module gen_xnor(7) $end
$upscope $end
$scope module gen_xnor(8) $end
$upscope $end
$scope module gen_xnor(9) $end
$upscope $end
$scope module gen_and(1) $end
$upscope $end
$scope module gen_and(2) $end
$upscope $end
$scope module gen_and(3) $end
$upscope $end
$scope module gen_and(4) $end
$upscope $end
$scope module gen_and(5) $end
$upscope $end
$scope module gen_and(6) $end
$upscope $end
$scope module gen_and(7) $end
$upscope $end
$scope module gen_and(8) $end
$upscope $end
$scope module gen_and(9) $end
$upscope $end
$upscope $end
$scope module comp655 $end
$var reg 10 u a[9:0] $end
$var reg 10 v b[9:0] $end
$var reg 1 w s $end
$var reg 10 x xnor_aux[9:0] $end
$var reg 10 y and_aux[9:0] $end
$scope module gen_xnor(0) $end
$upscope $end
$scope module gen_xnor(1) $end
$upscope $end
$scope module gen_xnor(2) $end
$upscope $end
$scope module gen_xnor(3) $end
$upscope $end
$scope module gen_xnor(4) $end
$upscope $end
$scope module gen_xnor(5) $end
$upscope $end
$scope module gen_xnor(6) $end
$upscope $end
$scope module gen_xnor(7) $end
$upscope $end
$scope module gen_xnor(8) $end
$upscope $end
$scope module gen_xnor(9) $end
$upscope $end
$scope module gen_and(1) $end
$upscope $end
$scope module gen_and(2) $end
$upscope $end
$scope module gen_and(3) $end
$upscope $end
$scope module gen_and(4) $end
$upscope $end
$scope module gen_and(5) $end
$upscope $end
$scope module gen_and(6) $end
$upscope $end
$scope module gen_and(7) $end
$upscope $end
$scope module gen_and(8) $end
$upscope $end
$scope module gen_and(9) $end
$upscope $end
$upscope $end
$scope module comp751 $end
$var reg 10 z a[9:0] $end
$var reg 10 { b[9:0] $end
$var reg 1 | s $end
$var reg 10 } xnor_aux[9:0] $end
$var reg 10 !" and_aux[9:0] $end
$scope module gen_xnor(0) $end
$upscope $end
$scope module gen_xnor(1) $end
$upscope $end
$scope module gen_xnor(2) $end
$upscope $end
$scope module gen_xnor(3) $end
$upscope $end
$scope module gen_xnor(4) $end
$upscope $end
$scope module gen_xnor(5) $end
$upscope $end
$scope module gen_xnor(6) $end
$upscope $end
$scope module gen_xnor(7) $end
$upscope $end
$scope module gen_xnor(8) $end
$upscope $end
$scope module gen_xnor(9) $end
$upscope $end
$scope module gen_and(1) $end
$upscope $end
$scope module gen_and(2) $end
$upscope $end
$scope module gen_and(3) $end
$upscope $end
$scope module gen_and(4) $end
$upscope $end
$scope module gen_and(5) $end
$upscope $end
$scope module gen_and(6) $end
$upscope $end
$scope module gen_and(7) $end
$upscope $end
$scope module gen_and(8) $end
$upscope $end
$scope module gen_and(9) $end
$upscope $end
$upscope $end
$scope module comp799 $end
$var reg 10 "" a[9:0] $end
$var reg 10 #" b[9:0] $end
$var reg 1 $" s $end
$var reg 10 %" xnor_aux[9:0] $end
$var reg 10 &" and_aux[9:0] $end
$scope module gen_xnor(0) $end
$upscope $end
$scope module gen_xnor(1) $end
$upscope $end
$scope module gen_xnor(2) $end
$upscope $end
$scope module gen_xnor(3) $end
$upscope $end
$scope module gen_xnor(4) $end
$upscope $end
$scope module gen_xnor(5) $end
$upscope $end
$scope module gen_xnor(6) $end
$upscope $end
$scope module gen_xnor(7) $end
$upscope $end
$scope module gen_xnor(8) $end
$upscope $end
$scope module gen_xnor(9) $end
$upscope $end
$scope module gen_and(1) $end
$upscope $end
$scope module gen_and(2) $end
$upscope $end
$scope module gen_and(3) $end
$upscope $end
$scope module gen_and(4) $end
$upscope $end
$scope module gen_and(5) $end
$upscope $end
$scope module gen_and(6) $end
$upscope $end
$scope module gen_and(7) $end
$upscope $end
$scope module gen_and(8) $end
$upscope $end
$scope module gen_and(9) $end
$upscope $end
$upscope $end
$scope module ffdhsync $end
$var reg 1 '" clk_i $end
$var reg 1 (" rst_i $end
$var reg 1 )" ena_i $end
$var reg 1 *" d_i $end
$var reg 1 +" q_o $end
$upscope $end
$scope module ffdhvidon $end
$var reg 1 ," clk_i $end
$var reg 1 -" rst_i $end
$var reg 1 ." ena_i $end
$var reg 1 /" d_i $end
$var reg 1 0" q_o $end
$upscope $end
$upscope $end
$upscope $end
$enddefinitions $end
#0
0!
0"
0#
1$
1%
0&
b0000000000 '
0(
0)
0*
1+
1,
0-
b0000000000 .
b0000000000 /
00
01
02
03
04
05
06
07
08
09
b0000000000 :
b0000000000 ;
b0000000000 <
b0000000000 =
0>
0?
1@
0A
0B
0C
0D
1E
0F
0G
0H
0I
1J
0K
0L
0M
0N
1O
0P
0Q
0R
0S
1T
0U
0V
0W
0X
1Y
0Z
0[
0\
0]
1^
0_
0`
0a
0b
1c
0d
0e
0f
0g
1h
0i
0j
0k
0l
1m
0n
0o
b0000000000 p
b1001111111 q
0r
b0110000000 s
b0000000000 t
b0000000000 u
b1010001111 v
0w
b0101110000 x
b0000000000 y
b0000000000 z
b1011101111 {
0|
b0100010000 }
b0000000000 !"
b0000000000 ""
b1100011111 #"
0$"
b0011100000 %"
b0000000000 &"
0'"
0("
0)"
1*"
0+"
0,"
0-"
0."
1/"
00"
#10000000
1!
1(
18
b0000000001 ;
b0000000001 <
1A
#20000000
1#
b0000000001 '
1*
b0000000001 .
b0000000001 /
17
b0000000001 :
b0000000011 ;
b0000000010 <
b0000000001 =
1>
0A
1B
1C
1F
1H
1M
1R
1W
1\
1a
1f
1k
b0000000001 p
b0110000001 s
b0000000001 t
b0000000001 u
b0101110001 x
b0000000001 y
b0000000001 z
b0100010001 }
b0000000001 !"
b0000000001 ""
b0011100001 %"
b0000000001 &"
1'"
1,"
#40000000
0#
0*
07
0>
0C
0H
0M
0R
0W
0\
0a
0f
0k
0'"
0,"
#60000000
1#
b0000000010 '
1*
b0000000010 .
b0000000010 /
17
b0000000010 :
b0000000001 ;
b0000000011 <
b0000000010 =
1>
1A
0B
1C
1F
1G
1H
0K
1M
1R
1W
1\
1a
1f
1k
b0000000010 p
b0110000010 s
b0000000000 t
b0000000010 u
b0101110010 x
b0000000000 y
b0000000010 z
b0100010010 }
b0000000000 !"
b0000000010 ""
b0011100010 %"
b0000000000 &"
1'"
1,"
#80000000
0#
0*
07
0>
0C
0H
0M
0R
0W
0\
0a
0f
0k
0'"
0,"
#100000000
1#
b0000000011 '
1*
b0000000011 .
b0000000011 /
17
b0000000011 :
b0000000111 ;
b0000000100 <
b0000000011 =
1>
0A
1B
1C
0F
1H
1K
1M
1R
1W
1\
1a
1f
1k
b0000000011 p
b0110000011 s
b0000000011 t
b0000000011 u
b0101110011 x
b0000000011 y
b0000000011 z
b0100010011 }
b0000000011 !"
b0000000011 ""
b0011100011 %"
b0000000011 &"
1'"
1,"
#120000000
0#
0*
07
0>
0C
0H
0M
0R
0W
0\
0a
0f
0k
0'"
0,"
#140000000
1#
b0000000100 '
1*
b0000000100 .
b0000000100 /
17
b0000000100 :
b0000000001 ;
b0000000101 <
b0000000100 =
1>
1A
0B
1C
0F
0G
1H
1K
1L
1M
0P
1R
1W
1\
1a
1f
1k
b0000000100 p
b0110000100 s
b0000000000 t
b0000000100 u
b0101110100 x
b0000000000 y
b0000000100 z
b0100010100 }
b0000000000 !"
b0000000100 ""
b0011100100 %"
b0000000000 &"
1'"
1,"
#160000000
0#
0*
07
0>
0C
0H
0M
0R
0W
0\
0a
0f
0k
0'"
0,"
#180000000
1#
b0000000101 '
1*
b0000000101 .
b0000000101 /
17
b0000000101 :
b0000000011 ;
b0000000110 <
b0000000101 =
1>
0A
1B
1C
1F
1H
1M
1R
1W
1\
1a
1f
1k
b0000000101 p
b0110000101 s
b0000000001 t
b0000000101 u
b0101110101 x
b0000000001 y
b0000000101 z
b0100010101 }
b0000000001 !"
b0000000101 ""
b0011100101 %"
b0000000001 &"
1'"
1,"
#200000000
0#
0*
07
0>
0C
0H
0M
0R
0W
0\
0a
0f
0k
0'"
0,"
#220000000
1#
b0000000110 '
1*
b0000000110 .
b0000000110 /
17
b0000000110 :
b0000000001 ;
b0000000111 <
b0000000110 =
1>
1A
0B
1C
1F
1G
1H
1K
1M
0P
1R
1W
1\
1a
1f
1k
b0000000110 p
b0110000110 s
b0000000000 t
b0000000110 u
b0101110110 x
b0000000000 y
b0000000110 z
b0100010110 }
b0000000000 !"
b0000000110 ""
b0011100110 %"
b0000000000 &"
1'"
1,"
#240000000
0#
0*
07
0>
0C
0H
0M
0R
0W
0\
0a
0f
0k
0'"
0,"
#260000000
1#
b0000000111 '
1*
b0000000111 .
b0000000111 /
17
b0000000111 :
b0000001111 ;
b0000001000 <
b0000000111 =
1>
0A
1B
1C
0F
1H
0K
1M
1P
1R
1W
1\
1a
1f
1k
b0000000111 p
b0110000111 s
b0000000111 t
b0000000111 u
b0101110111 x
b0000000111 y
b0000000111 z
b0100010111 }
b0000000111 !"
b0000000111 ""
b0011100111 %"
b0000000111 &"
1'"
1,"
#280000000
0#
0*
07
0>
0C
0H
0M
0R
0W
0\
0a
0f
0k
0'"
0,"
#300000000
1#
b0000001000 '
1*
b0000001000 .
b0000001000 /
17
b0000001000 :
b0000000001 ;
b0000001001 <
b0000001000 =
1>
1A
0B
1C
0F
0G
1H
0K
0L
1M
1P
1Q
1R
0U
1W
1\
1a
1f
1k
b0000001000 p
b0110001000 s
b0000000000 t
b0000001000 u
b0101111000 x
b0000000000 y
b0000001000 z
b0100011000 }
b0000000000 !"
b0000001000 ""
b0011101000 %"
b0000000000 &"
1'"
1,"
#320000000
0#
0*
07
0>
0C
0H
0M
0R
0W
0\
0a
0f
0k
0'"
0,"
#340000000
1#
b0000001001 '
1*
b0000001001 .
b0000001001 /
17
b0000001001 :
b0000000011 ;
b0000001010 <
b0000001001 =
1>
0A
1B
1C
1F
1H
1M
1R
1W
1\
1a
1f
1k
b0000001001 p
b0110001001 s
b0000000001 t
b0000001001 u
b0101111001 x
b0000000001 y
b0000001001 z
b0100011001 }
b0000000001 !"
b0000001001 ""
b0011101001 %"
b0000000001 &"
1'"
1,"
#360000000
0#
0*
07
0>
0C
0H
0M
0R
0W
0\
0a
0f
0k
0'"
0,"
#380000000
1#
b0000001010 '
1*
b0000001010 .
b0000001010 /
17
b0000001010 :
b0000000001 ;
b0000001011 <
b0000001010 =
1>
1A
0B
1C
1F
1G
1H
0K
1M
1R
1W
1\
1a
1f
1k
b0000001010 p
b0110001010 s
b0000000000 t
b0000001010 u
b0101111010 x
b0000000000 y
b0000001010 z
b0100011010 }
b0000000000 !"
b0000001010 ""
b0011101010 %"
b0000000000 &"
1'"
1,"
#400000000
0#
0*
07
0>
0C
0H
0M
0R
0W
0\
0a
0f
0k
0'"
0,"
#420000000
1#
b0000001011 '
1*
b0000001011 .
b0000001011 /
17
b0000001011 :
b0000000111 ;
b0000001100 <
b0000001011 =
1>
0A
1B
1C
0F
1H
1K
1M
1R
1W
1\
1a
1f
1k
b0000001011 p
b0110001011 s
b0000000011 t
b0000001011 u
b0101111011 x
b0000000011 y
b0000001011 z
b0100011011 }
b0000000011 !"
b0000001011 ""
b0011101011 %"
b0000000011 &"
1'"
1,"
#440000000
0#
0*
07
0>
0C
0H
0M
0R
0W
0\
0a
0f
0k
0'"
0,"
#460000000
1#
b0000001100 '
1*
b0000001100 .
b0000001100 /
17
b0000001100 :
b0000000001 ;
b0000001101 <
b0000001100 =
1>
1A
0B
1C
0F
0G
1H
1K
1L
1M
1P
1R
0U
1W
1\
1a
1f
1k
b0000001100 p
b0110001100 s
b0000000000 t
b0000001100 u
b0101111100 x
b0000000000 y
b0000001100 z
b0100011100 }
b0000000000 !"
b0000001100 ""
b0011101100 %"
b0000000000 &"
1'"
1,"
#480000000
0#
0*
07
0>
0C
0H
0M
0R
0W
0\
0a
0f
0k
0'"
0,"
#500000000
1#
b0000001101 '
1*
b0000001101 .
b0000001101 /
17
b0000001101 :
b0000000011 ;
b0000001110 <
b0000001101 =
1>
0A
1B
1C
1F
1H
1M
1R
1W
1\
1a
1f
1k
b0000001101 p
b0110001101 s
b0000000001 t
b0000001101 u
b0101111101 x
b0000000001 y
b0000001101 z
b0100011101 }
b0000000001 !"
b0000001101 ""
b0011101101 %"
b0000000001 &"
1'"
1,"
#520000000
0#
0*
07
0>
0C
0H
0M
0R
0W
0\
0a
0f
0k
0'"
0,"
#540000000
1#
b0000001110 '
1*
b0000001110 .
b0000001110 /
17
b0000001110 :
b0000000001 ;
b0000001111 <
b0000001110 =
1>
1A
0B
1C
1F
1G
1H
1K
1M
1P
1R
0U
1W
1\
1a
1f
1k
b0000001110 p
b0110001110 s
b0000000000 t
b0000001110 u
b0101111110 x
b0000000000 y
b0000001110 z
b0100011110 }
b0000000000 !"
b0000001110 ""
b0011101110 %"
b0000000000 &"
1'"
1,"
#560000000
0#
0*
07
0>
0C
0H
0M
0R
0W
0\
0a
0f
0k
0'"
0,"
#580000000
1#
b0000001111 '
1*
b0000001111 .
b0000001111 /
17
b0000001111 :
b0000011111 ;
b0000010000 <
b0000001111 =
1>
0A
1B
1C
0F
1H
0K
1M
0P
1R
1U
1W
1\
1a
1f
1k
b0000001111 p
b0110001111 s
b0000001111 t
b0000001111 u
b0101111111 x
b0001111111 y
b0000001111 z
b0100011111 }
b0000011111 !"
b0000001111 ""
b0011101111 %"
b0000001111 &"
1'"
1,"
#600000000
0#
0*
07
0>
0C
0H
0M
0R
0W
0\
0a
0f
0k
0'"
0,"
#620000000
1#
b0000010000 '
1*
b0000010000 .
b0000010000 /
17
b0000010000 :
b0000000001 ;
b0000010001 <
b0000010000 =
1>
1A
0B
1C
0F
0G
1H
0K
0L
1M
0P
0Q
1R
1U
1V
1W
0Z
1\
1a
1f
1k
b0000010000 p
b0110010000 s
b0000000000 t
b0000010000 u
b0101100000 x
b0000000000 y
b0000010000 z
b0100000000 }
b0000000000 !"
b0000010000 ""
b0011110000 %"
b0000000000 &"
1'"
1,"
#640000000
0#
0*
07
0>
0C
0H
0M
0R
0W
0\
0a
0f
0k
0'"
0,"
#660000000
1#
b0000010001 '
1*
b0000010001 .
b0000010001 /
17
b0000010001 :
b0000000011 ;
b0000010010 <
b0000010001 =
1>
0A
1B
1C
1F
1H
1M
1R
1W
1\
1a
1f
1k
b0000010001 p
b0110010001 s
b0000000001 t
b0000010001 u
b0101100001 x
b0000000001 y
b0000010001 z
b0100000001 }
b0000000001 !"
b0000010001 ""
b0011110001 %"
b0000000001 &"
1'"
1,"
#680000000
0#
0*
07
0>
0C
0H
0M
0R
0W
0\
0a
0f
0k
0'"
0,"
#700000000
1#
b0000010010 '
1*
b0000010010 .
b0000010010 /
17
b0000010010 :
b0000000001 ;
b0000010011 <
b0000010010 =
1>
1A
0B
1C
1F
1G
1H
0K
1M
1R
1W
1\
1a
1f
1k
b0000010010 p
b0110010010 s
b0000000000 t
b0000010010 u
b0101100010 x
b0000000000 y
b0000010010 z
b0100000010 }
b0000000000 !"
b0000010010 ""
b0011110010 %"
b0000000000 &"
1'"
1,"
#720000000
0#
0*
07
0>
0C
0H
0M
0R
0W
0\
0a
0f
0k
0'"
0,"
#740000000
1#
b0000010011 '
1*
b0000010011 .
b0000010011 /
17
b0000010011 :
b0000000111 ;
b0000010100 <
b0000010011 =
1>
0A
1B
1C
0F
1H
1K
1M
1R
1W
1\
1a
1f
1k
b0000010011 p
b0110010011 s
b0000000011 t
b0000010011 u
b0101100011 x
b0000000011 y
b0000010011 z
b0100000011 }
b0000000011 !"
b0000010011 ""
b0011110011 %"
b0000000011 &"
1'"
1,"
#760000000
0#
0*
07
0>
0C
0H
0M
0R
0W
0\
0a
0f
0k
0'"
0,"
#780000000
1#
b0000010100 '
1*
b0000010100 .
b0000010100 /
17
b0000010100 :
b0000000001 ;
b0000010101 <
b0000010100 =
1>
1A
0B
1C
0F
0G
1H
1K
1L
1M
0P
1R
1W
1\
1a
1f
1k
b0000010100 p
b0110010100 s
b0000000000 t
b0000010100 u
b0101100100 x
b0000000000 y
b0000010100 z
b0100000100 }
b0000000000 !"
b0000010100 ""
b0011110100 %"
b0000000000 &"
1'"
1,"
#800000000
0#
0*
07
0>
0C
0H
0M
0R
0W
0\
0a
0f
0k
0'"
0,"
#820000000
1#
b0000010101 '
1*
b0000010101 .
b0000010101 /
17
b0000010101 :
b0000000011 ;
b0000010110 <
b0000010101 =
1>
0A
1B
1C
1F
1H
1M
1R
1W
1\
1a
1f
1k
b0000010101 p
b0110010101 s
b0000000001 t
b0000010101 u
b0101100101 x
b0000000001 y
b0000010101 z
b0100000101 }
b0000000001 !"
b0000010101 ""
b0011110101 %"
b0000000001 &"
1'"
1,"
#840000000
0#
0*
07
0>
0C
0H
0M
0R
0W
0\
0a
0f
0k
0'"
0,"
#860000000
1#
b0000010110 '
1*
b0000010110 .
b0000010110 /
17
b0000010110 :
b0000000001 ;
b0000010111 <
b0000010110 =
1>
1A
0B
1C
1F
1G
1H
1K
1M
0P
1R
1W
1\
1a
1f
1k
b0000010110 p
b0110010110 s
b0000000000 t
b0000010110 u
b0101100110 x
b0000000000 y
b0000010110 z
b0100000110 }
b0000000000 !"
b0000010110 ""
b0011110110 %"
b0000000000 &"
1'"
1,"
#880000000
0#
0*
07
0>
0C
0H
0M
0R
0W
0\
0a
0f
0k
0'"
0,"
#900000000
1#
b0000010111 '
1*
b0000010111 .
b0000010111 /
17
b0000010111 :
b0000001111 ;
b0000011000 <
b0000010111 =
1>
0A
1B
1C
0F
1H
0K
1M
1P
1R
1W
1\
1a
1f
1k
b0000010111 p
b0110010111 s
b0000000111 t
b0000010111 u
b0101100111 x
b0000000111 y
b0000010111 z
b0100000111 }
b0000000111 !"
b0000010111 ""
b0011110111 %"
b0000000111 &"
1'"
1,"
#920000000
0#
0*
07
0>
0C
0H
0M
0R
0W
0\
0a
0f
0k
0'"
0,"
#940000000
1#
b0000011000 '
1*
b0000011000 .
b0000011000 /
17
b0000011000 :
b0000000001 ;
b0000011001 <
b0000011000 =
1>
1A
0B
1C
0F
0G
1H
0K
0L
1M
1P
1Q
1R
1U
1W
0Z
1\
1a
1f
1k
b0000011000 p
b0110011000 s
b0000000000 t
b0000011000 u
b0101101000 x
b0000000000 y
b0000011000 z
b0100001000 }
b0000000000 !"
b0000011000 ""
b0011111000 %"
b0000000000 &"
1'"
1,"
#960000000
0#
0*
07
0>
0C
0H
0M
0R
0W
0\
0a
0f
0k
0'"
0,"
