bloques_codigo/Codigos/ffd.vhd
-- Flip - Flop D con enable y reset
-- Estudiante: Fernandez, Rocio
library IEEE;
use IEEE.std_logic_1164.all;

entity ffd is
	port (
		clk_i : in std_logic; -- Clock
		rst_i : in std_logic; -- Reset
		ena_i : in std_logic; -- Enable
		d_i   : in std_logic; -- Dato
		q_o   : out std_logic -- Salida
	);
end entity;

architecture ffd_arc of ffd is
begin
	process(clk_i)
	begin
		if rising_edge(clk_i) then 
			if rst_i = '1' then         -- Reset activo
				q_o <= '0';
			elsif ena_i = '1' then      -- Enable activo
				q_o <= d_i;
			end if;
		end if;
	end process;
end architecture;

bloques_codigo/Codigos/comp_Nb.vhd
-- Comparador de N bits
-- Estudiante: Fernandez, Rocio


entity comp_Nb is
  generic(N: natural := 10);
  port(
    a: in  bit_vector(N-1 downto 0);  --  A
    b: in  bit_vector(N-1 downto 0);  -- B
    s: out bit                       -- Salida: '1' si A = B
  );
end;

architecture comp_Nb_arq of comp_Nb is
  signal xnor_aux: bit_vector(N-1 downto 0);
  signal and_aux:  bit_vector(N-1 downto 0);
begin

  -- Compara bit a bit usando XNOR
  gen_xnor: for i in 0 to N-1 generate
    xnor_aux(i) <= a(i) xnor b(i);
  end generate;

  -- And de todos los bits (en cascada)
  and_aux(0) <= xnor_aux(0);
  gen_and: for i in 1 to N-1 generate
    and_aux(i) <= and_aux(i-1) and xnor_aux(i);
  end generate;

  -- Salida: '1' si todos los bits coinciden
  s <= and_aux(N-1);

end architecture;

bloques_codigo/Codigos/cont_bin_gen.vhd
-- CONTADOR BINARIO DE 16 bits


entity cont_bin_gen is
  generic(
      N: natural := 4 
  );
  port (
    clk_bin_gen : in bit;
    ena_bin_gen : in bit;
    rst_bin_gen : in bit;
    salida_gen  : out bit_vector(N-1 downto 0)
  );
end entity;

architecture cont_bin_gen_arq of cont_bin_gen is

  component ffd is
    port (
      clk_i   : in  bit;
      rst_i   : in  bit;
      ena_i   : in  bit;
      d_i     : in  bit;
      q_o     : out bit
    );
  end component;

    signal salAnd   : bit_vector(N-1 downto 0);  
    signal salXor   : bit_vector(N-1 downto 0); 
    -- signal entrada  : bit_vector(9 downto 0);
    signal salida   : bit_vector(N-1 downto 0);

begin
    salAnd(0) <= ena_bin_gen;
    salXor(0) <= salAnd(0) xor salida(0);

    cont_bin10: for i in 0 to N-1 generate
        etapa_0: if i = 0 generate
            ffd0: ffd port map (
                        clk_i => clk_bin_gen,
                        rst_i => rst_bin_gen,
                        ena_i => '1',
                        d_i => salXor(0),
                        q_o => salida(0)
                    );
        end generate;
        
        etapa_1: if i > 0 generate
            --conexiones de las N etapas
            salAnd(i) <= salAnd(i-1) and salida(i-1);
            salXor(i) <= salAnd(i) xor salida(i);

            ffdN: ffd port map (
                        clk_i => clk_bin_gen,
                        rst_i => rst_bin_gen,
                        ena_i => '1',
                        d_i => salXor(i),
                        q_o => salida(i)
                    );
        end generate;
    end generate;
    
    salida_gen <= salida;
end;

bloques_codigo/Codigos/vsync/Fuentes/vsync.vhd
-- SINCRONISMO VERTICAL
-- Estudiante : Fernandez, Rocio

entity vsync is 
    port (
        ena_vsync   : in bit;
        rst_vsync   : in bit;
        clk_vsync   : in bit;
        v_sync      : out bit;
        v_vidon     : out bit;
        cont_v      : out bit_vector(9 downto 0)
    );
end;

architecture vsync_arq of vsync is 

   -- contador binario, necesito que cuente hasta 525 por ende que sea de 10 bits
   component cont_bin_gen is 
    generic(
        N: natural := 10 
    );
    port (
        clk_bin_gen : in bit;
        ena_bin_gen : in bit;
        rst_bin_gen : in bit;
        salida_gen  : out bit_vector(N-1 downto 0)
    );
    end component;

    component  comp_Nb is
        port ( 
            A       : in bit_vector(9 downto 0);
            B       : in bit_vector(9 downto 0);
            s  : out bit
        );
    end component;

    component ffd is 
        port(
            clk_i   : in bit;
            rst_i   : in bit;
            ena_i   : in bit;
            d_i     : in bit;
            q_o     : out bit
        );
    end component;

    signal cuenta_v     : bit_vector(9 downto 0) := (9 downto 0 => '0');
    signal reset_aux_v  : bit := '0';
    signal comp_479     : bit := '0';   -- 0111011111
    signal comp_489     : bit := '0';   -- 0111101001
    signal comp_491     : bit := '0';   -- 0111101011
    signal comp_524     : bit := '0';   -- 1000001100
    signal ena_479      : bit := '0';   -- '1' si ena general = '1' y cuenta_V = 479
    signal ena_489      : bit := '0';   -- '1' si ena general = '1' y cuenta_V = 489
    signal rst_491      : bit := '0';   -- '1' si ena general = '1' y cuenta_V = 491
    signal sal_vsync    : bit := '0';
    signal sal_vvidon   : bit := '0';

begin

    cont525: cont_bin_gen
        port map(
            clk_bin_gen => clk_vsync,
            ena_bin_gen => ena_vsync,
            rst_bin_gen => reset_aux_v,
            salida_gen  => cuenta_v
        );

    comp479: comp_Nb
        port map(
            A       => cuenta_v,
            B       => "0111011111", 
            s  => comp_479
        );

    comp489: comp_Nb
        port map(
            A       => cuenta_v,
            B       => "0111101001",
            s  => comp_489
        );

    comp491: comp_Nb
        port map(
            A       => cuenta_v,
            B       => "0111101011",
            s  => comp_491
        );

    comp524: comp_Nb
        port map(
            A       => cuenta_v,
            B       => "1000001100", 
            s  => comp_524
        );

    ffdvsync: ffd
        port map(
            clk_i   => clk_vsync,
            rst_i   => rst_491,
            ena_i   => ena_489,
            d_i     => '1',
            q_o     => sal_vsync
        );

    ffdvvidon: ffd
        port map(
            clk_i   => clk_vsync,
            rst_i   => reset_aux_v,
            ena_i   => ena_479,
            d_i     => '1',
            q_o     => sal_vvidon
        );

    v_sync       <= not sal_vsync;
    v_vidon      <= not sal_vvidon;
    cont_v      <= cuenta_v;    
    ena_479     <= comp_479 and ena_vsync;
    ena_489     <= comp_489 and ena_vsync;
    rst_491     <= comp_491 and ena_vsync;
    reset_aux_v <= ena_vsync and (rst_vsync or comp_524);

end;

bloques_codigo/Testbenchs/vsync_tb.vhd
-- Test del sincronismo vertica

library IEEE;
use IEEE.bit_1164.all;
use IEEE.numeric_std.all;

entity vsync_tb is 
end;

architecture vsync_tb_arq of vsync_tb is 

    component vsync is 
        port (
            ena_vsync   : in bit;
            rst_vsync   : in bit;
            clk_vsync   : in bit;
            v_sync      : out bit;
            v_vidon     : out bit;
            cont_v      : out bit_vector(9 downto 0)
        );
    end component;

    signal ena_vsync_tb   : bit := '0';
    signal rst_vsync_tb   : bit := '0';
    signal clk_vsync_tb   : bit := '0';
    signal v_sync_tb      : bit := '0';
    signal v_vidon_tb     : bit := '0';
    signal cont_v_tb      : bit_vector(9 downto 0) := (9 downto 0 => '0');

begin

    ena_vsync_tb <= '1' after 10 ns;
    clk_vsync_tb <= not clk_vsync_tb after 20 ns;
    -- rst_vsync_tb <= '1' after 30 ns, '0' after 40 ns;

    DUT: vsync
        port map(
            ena_vsync   => ena_vsync_tb,
            rst_vsync   => rst_vsync_tb,
            clk_vsync   => clk_vsync_tb,
            v_sync      => v_sync_tb,
            v_vidon     => v_vidon_tb,
            cont_v      => cont_v_tb
        );
end;

bloques_codigo/Codigos/vsync/Simulacion/vsync_tb.vcd
$date
  Thu Jul 17 12:08:09 2025
$end
$version
  GHDL v0
$end
$timescale
  1 fs
$end
$scope module standard $end
$upscope $end
$scope module vsync_tb $end
$var reg 1 ! ena_vsync_tb $end
$var reg 1 " rst_vsync_tb $end
$var reg 1 # clk_vsync_tb $end
$var reg 1 $ v_sync_tb $end
$var reg 1 % v_vidon_tb $end
$var reg 10 & cont_v_tb[9:0] $end
$scope module dut $end
$var reg 1 ' ena_vsync $end
$var reg 1 ( rst_vsync $end
$var reg 1 ) clk_vsync $end
$var reg 1 * v_sync $end
$var reg 1 + v_vidon $end
$var reg 10 , cont_v[9:0] $end
$var reg 10 - cuenta_v[9:0] $end
$var reg 1 . reset_aux_v $end
$var reg 1 / comp_479 $end
$var reg 1 0 comp_489 $end
$var reg 1 1 comp_491 $end
$var reg 1 2 comp_524 $end
$var reg 1 3 ena_479 $end
$var reg 1 4 ena_489 $end
$var reg 1 5 rst_491 $end
$var reg 1 6 sal_vsync $end
$var reg 1 7 sal_vvidon $end
$scope module cont525 $end
$var reg 1 8 clk_bin_gen $end
$var reg 1 9 ena_bin_gen $end
$var reg 1 : rst_bin_gen $end
$var reg 10 ; salida_gen[9:0] $end
$var reg 10 < saland[9:0] $end
$var reg 10 = salxor[9:0] $end
$var reg 10 > salida[9:0] $end
$scope module cont_bin10(0) $end
$scope module etapa_0 $end
$scope module ffd0 $end
$var reg 1 ? clk_i $end
$var reg 1 @ rst_i $end
$var reg 1 A ena_i $end
$var reg 1 B d_i $end
$var reg 1 C q_o $end
$upscope $end
$upscope $end
$upscope $end
$scope module cont_bin10(1) $end
$scope module etapa_1 $end
$scope module ffdn $end
$var reg 1 D clk_i $end
$var reg 1 E rst_i $end
$var reg 1 F ena_i $end
$var reg 1 G d_i $end
$var reg 1 H q_o $end
$upscope $end
$upscope $end
$upscope $end
$scope module cont_bin10(2) $end
$scope module etapa_1 $end
$scope module ffdn $end
$var reg 1 I clk_i $end
$var reg 1 J rst_i $end
$var reg 1 K ena_i $end
$var reg 1 L d_i $end
$var reg 1 M q_o $end
$upscope $end
$upscope $end
$upscope $end
$scope module cont_bin10(3) $end
$scope module etapa_1 $end
$scope module ffdn $end
$var reg 1 N clk_i $end
$var reg 1 O rst_i $end
$var reg 1 P ena_i $end
$var reg 1 Q d_i $end
$var reg 1 R q_o $end
$upscope $end
$upscope $end
$upscope $end
$scope module cont_bin10(4) $end
$scope module etapa_1 $end
$scope module ffdn $end
$var reg 1 S clk_i $end
$var reg 1 T rst_i $end
$var reg 1 U ena_i $end
$var reg 1 V d_i $end
$var reg 1 W q_o $end
$upscope $end
$upscope $end
$upscope $end
$scope module cont_bin10(5) $end
$scope module etapa_1 $end
$scope module ffdn $end
$var reg 1 X clk_i $end
$var reg 1 Y rst_i $end
$var reg 1 Z ena_i $end
$var reg 1 [ d_i $end
$var reg 1 \ q_o $end
$upscope $end
$upscope $end
$upscope $end
$scope module cont_bin10(6) $end
$scope module etapa_1 $end
$scope module ffdn $end
$var reg 1 ] clk_i $end
$var reg 1 ^ rst_i $end
$var reg 1 _ ena_i $end
$var reg 1 ` d_i $end
$var reg 1 a q_o $end
$upscope $end
$upscope $end
$upscope $end
$scope module cont_bin10(7) $end
$scope module etapa_1 $end
$scope module ffdn $end
$var reg 1 b clk_i $end
$var reg 1 c rst_i $end
$var reg 1 d ena_i $end
$var reg 1 e d_i $end
$var reg 1 f q_o $end
$upscope $end
$upscope $end
$upscope $end
$scope module cont_bin10(8) $end
$scope module etapa_1 $end
$scope module ffdn $end
$var reg 1 g clk_i $end
$var reg 1 h rst_i $end
$var reg 1 i ena_i $end
$var reg 1 j d_i $end
$var reg 1 k q_o $end
$upscope $end
$upscope $end
$upscope $end
$scope module cont_bin10(9) $end
$scope module etapa_1 $end
$scope module ffdn $end
$var reg 1 l clk_i $end
$var reg 1 m rst_i $end
$var reg 1 n ena_i $end
$var reg 1 o d_i $end
$var reg 1 p q_o $end
$upscope $end
$upscope $end
$upscope $end
$upscope $end
$scope module comp479 $end
$var reg 10 q a[9:0] $end
$var reg 10 r b[9:0] $end
$var reg 1 s s $end
$var reg 10 t xnor_aux[9:0] $end
$var reg 10 u and_aux[9:0] $end
$scope module gen_xnor(0) $end
$upscope $end
$scope module gen_xnor(1) $end
$upscope $end
$scope module gen_xnor(2) $end
$upscope $end
$scope module gen_xnor(3) $end
$upscope $end
$scope module gen_xnor(4) $end
$upscope $end
$scope module gen_xnor(5) $end
$upscope $end
$scope module gen_xnor(6) $end
$upscope $end
$scope module gen_xnor(7) $end
$upscope $end
$scope module gen_xnor(8) $end
$upscope $end
$scope module gen_xnor(9) $end
$upscope $end
$scope module gen_and(1) $end
$upscope $end
$scope module gen_and(2) $end
$upscope $end
$scope module gen_and(3) $end
$upscope $end
$scope module gen_and(4) $end
$upscope $end
$scope module gen_and(5) $end
$upscope $end
$scope module gen_and(6) $end
$upscope $end
$scope module gen_and(7) $end
$upscope $end
$scope module gen_and(8) $end
$upscope $end
$scope module gen_and(9) $end
$upscope $end
$upscope $end
$scope module comp489 $end
$var reg 10 v a[9:0] $end
$var reg 10 w b[9:0] $end
$var reg 1 x s $end
$var reg 10 y xnor_aux[9:0] $end
$var reg 10 z and_aux[9:0] $end
$scope module gen_xnor(0) $end
$upscope $end
$scope module gen_xnor(1) $end
$upscope $end
$scope module gen_xnor(2) $end
$upscope $end
$scope module gen_xnor(3) $end
$upscope $end
$scope module gen_xnor(4) $end
$upscope $end
$scope module gen_xnor(5) $end
$upscope $end
$scope module gen_xnor(6) $end
$upscope $end
$scope module gen_xnor(7) $end
$upscope $end
$scope module gen_xnor(8) $end
$upscope $end
$scope module gen_xnor(9) $end
$upscope $end
$scope module gen_and(1) $end
$upscope $end
$scope module gen_and(2) $end
$upscope $end
$scope module gen_and(3) $end
$upscope $end
$scope module gen_and(4) $end
$upscope $end
$scope module gen_and(5) $end
$upscope $end
$scope module gen_and(6) $end
$upscope $end
$scope module gen_and(7) $end
$upscope $end
$scope module gen_and(8) $end
$upscope $end
$scope module gen_and(9) $end
$upscope $end
$upscope $end
$scope module comp491 $end
$var reg 10 { a[9:0] $end
$var reg 10 | b[9:0] $end
$var reg 1 } s $end
$var reg 10 !" xnor_aux[9:0] $end
$var reg 10 "" and_aux[9:0] $end
$scope module gen_xnor(0) $end
$upscope $end
$scope module gen_xnor(1) $end
$upscope $end
$scope module gen_xnor(2) $end
$upscope $end
$scope module gen_xnor(3) $end
$upscope $end
$scope module gen_xnor(4) $end
$upscope $end
$scope module gen_xnor(5) $end
$upscope $end
$scope module gen_xnor(6) $end
$upscope $end
$scope module gen_xnor(7) $end
$upscope $end
$scope module gen_xnor(8) $end
$upscope $end
$scope module gen_xnor(9) $end
$upscope $end
$scope module gen_and(1) $end
$upscope $end
$scope module gen_and(2) $end
$upscope $end
$scope module gen_and(3) $end
$upscope $end
$scope module gen_and(4) $end
$upscope $end
$scope module gen_and(5) $end
$upscope $end
$scope module gen_and(6) $end
$upscope $end
$scope module gen_and(7) $end
$upscope $end
$scope module gen_and(8) $end
$upscope $end
$scope module gen_and(9) $end
$upscope $end
$upscope $end
$scope module comp524 $end
$var reg 10 #" a[9:0] $end
$var reg 10 $" b[9:0] $end
$var reg 1 %" s $end
$var reg 10 &" xnor_aux[9:0] $end
$var reg 10 '" and_aux[9:0] $end
$scope module gen_xnor(0) $end
$upscope $end
$scope module gen_xnor(1) $end
$upscope $end
$scope module gen_xnor(2) $end
$upscope $end
$scope module gen_xnor(3) $end
$upscope $end
$scope module gen_xnor(4) $end
$upscope $end
$scope module gen_xnor(5) $end
$upscope $end
$scope module gen_xnor(6) $end
$upscope $end
$scope module gen_xnor(7) $end
$upscope $end
$scope module gen_xnor(8) $end
$upscope $end
$scope module gen_xnor(9) $end
$upscope $end
$scope module gen_and(1) $end
$upscope $end
$scope module gen_and(2) $end
$upscope $end
$scope module gen_and(3) $end
$upscope $end
$scope module gen_and(4) $end
$upscope $end
$scope module gen_and(5) $end
$upscope $end
$scope module gen_and(6) $end
$upscope $end
$scope module gen_and(7) $end
$upscope $end
$scope module gen_and(8) $end
$upscope $end
$scope module gen_and(9) $end
$upscope $end
$upscope $end
$scope module ffdvsync $end
$var reg 1 (" clk_i $end
$var reg 1 )" rst_i $end
$var reg 1 *" ena_i $end
$var reg 1 +" d_i $end
$var reg 1 ," q_o $end
$upscope $end
$scope module ffdvvidon $end
$var reg 1 -" clk_i $end
$var reg 1 ." rst_i $end
$var reg 1 /" ena_i $end
$var reg 1 0" d_i $end
$var reg 1 1" q_o $end
$upscope $end
$upscope $end
$upscope $end
$enddefinitions $end
#0
0!
0"
0#
1$
1%
b0000000000 &
0'
0(
0)
1*
1+
b0000000000 ,
b0000000000 -
0.
0/
00
01
02
03
04
05
06
07
08
09
0:
b0000000000 ;
b0000000000 <
b0000000000 =
b0000000000 >
0?
0@
1A
0B
0C
0D
0E
1F
0G
0H
0I
0J
1K
0L
0M
0N
0O
1P
0Q
0R
0S
0T
1U
0V
0W
0X
0Y
1Z
0[
0\
0]
0^
1_
0`
0a
0b
0c
1d
0e
0f
0g
0h
1i
0j
0k
0l
0m
1n
0o
0p
b0000000000 q
b0111011111 r
0s
b1000100000 t
b0000000000 u
b0000000000 v
b0111101001 w
0x
b1000010110 y
b0000000000 z
b0000000000 {
b0111101011 |
0}
b1000010100 !"
b0000000000 ""
b0000000000 #"
b1000001100 $"
0%"
b0111110011 &"
b0000000011 '"
0("
0)"
0*"
1+"
0,"
0-"
0."
0/"
10"
01"
#10000000
1!
1'
19
b0000000001 <
b0000000001 =
1B
#20000000
1#
b0000000001 &
1)
b0000000001 ,
b0000000001 -
18
b0000000001 ;
b0000000011 <
b0000000010 =
b0000000001 >
1?
0B
1C
1D
1G
1I
1N
1S
1X
1]
1b
1g
1l
b0000000001 q
b1000100001 t
b0000000001 u
b0000000001 v
b1000010111 y
b0000000111 z
b0000000001 {
b1000010101 !"
b0000000001 ""
b0000000001 #"
b0111110010 &"
b0000000000 '"
1("
1-"
#40000000
0#
0)
08
0?
0D
0I
0N
0S
0X
0]
0b
0g
0l
0("
0-"
#60000000
1#
b0000000010 &
1)
b0000000010 ,
b0000000010 -
18
b0000000010 ;
b0000000001 <
b0000000011 =
b0000000010 >
1?
1B
0C
1D
1G
1H
1I
0L
1N
1S
1X
1]
1b
1g
1l
b0000000010 q
b1000100010 t
b0000000000 u
b0000000010 v
b1000010100 y
b0000000000 z
b0000000010 {
b1000010110 !"
b0000000000 ""
b0000000010 #"
b0111110001 &"
b0000000001 '"
1("
1-"
#80000000
0#
0)
08
0?
0D
0I
0N
0S
0X
0]
0b
0g
0l
0("
0-"
#100000000
1#
b0000000011 &
1)
b0000000011 ,
b0000000011 -
18
b0000000011 ;
b0000000111 <
b0000000100 =
b0000000011 >
1?
0B
1C
1D
0G
1I
1L
1N
1S
1X
1]
1b
1g
1l
b0000000011 q
b1000100011 t
b0000000011 u
b0000000011 v
b1000010101 y
b0000000001 z
b0000000011 {
b1000010111 !"
b0000000111 ""
b0000000011 #"
b0111110000 &"
b0000000000 '"
1("
1-"
#120000000
0#
0)
08
0?
0D
0I
0N
0S
0X
0]
0b
0g
0l
0("
0-"
#140000000
1#
b0000000100 &
1)
b0000000100 ,
b0000000100 -
18
b0000000100 ;
b0000000001 <
b0000000101 =
b0000000100 >
1?
1B
0C
1D
0G
0H
1I
1L
1M
1N
0Q
1S
1X
1]
1b
1g
1l
b0000000100 q
b1000100100 t
b0000000000 u
b0000000100 v
b1000010010 y
b0000000000 z
b0000000100 {
b1000010000 !"
b0000000000 ""
b0000000100 #"
b0111110111 &"
b0000000111 '"
1("
1-"
#160000000
0#
0)
08
0?
0D
0I
0N
0S
0X
0]
0b
0g
0l
0("
0-"
#180000000
1#
b0000000101 &
1)
b0000000101 ,
b0000000101 -
18
b0000000101 ;
b0000000011 <
b0000000110 =
b0000000101 >
1?
0B
1C
1D
1G
1I
1N
1S
1X
1]
1b
1g
1l
b0000000101 q
b1000100101 t
b0000000001 u
b0000000101 v
b1000010011 y
b0000000011 z
b0000000101 {
b1000010001 !"
b0000000001 ""
b0000000101 #"
b0111110110 &"
b0000000000 '"
1("
1-"
#200000000
0#
0)
08
0?
0D
0I
0N
0S
0X
0]
0b
0g
0l
0("
0-"
#220000000
1#
b0000000110 &
1)
b0000000110 ,
b0000000110 -
18
b0000000110 ;
b0000000001 <
b0000000111 =
b0000000110 >
1?
1B
0C
1D
1G
1H
1I
1L
1N
0Q
1S
1X
1]
1b
1g
1l
b0000000110 q
b1000100110 t
b0000000000 u
b0000000110 v
b1000010000 y
b0000000000 z
b0000000110 {
b1000010010 !"
b0000000000 ""
b0000000110 #"
b0111110101 &"
b0000000001 '"
1("
1-"
#240000000
0#
0)
08
0?
0D
0I
0N
0S
0X
0]
0b
0g
0l
0("
0-"
#260000000
1#
b0000000111 &
1)
b0000000111 ,
b0000000111 -
18
b0000000111 ;
b0000001111 <
b0000001000 =
b0000000111 >
1?
0B
1C
1D
0G
1I
0L
1N
1Q
1S
1X
1]
1b
1g
1l
b0000000111 q
b1000100111 t
b0000000111 u
b0000000111 v
b1000010001 y
b0000000001 z
b0000000111 {
b1000010011 !"
b0000000011 ""
b0000000111 #"
b0111110100 &"
b0000000000 '"
1("
1-"
#280000000
0#
0)
08
0?
0D
0I
0N
0S
0X
0]
0b
0g
0l
0("
0-"
#300000000
1#
b0000001000 &
1)
b0000001000 ,
b0000001000 -
18
b0000001000 ;
b0000000001 <
b0000001001 =
b0000001000 >
1?
1B
0C
1D
0G
0H
1I
0L
0M
1N
1Q
1R
1S
0V
1X
1]
1b
1g
1l
b0000001000 q
b1000101000 t
b0000000000 u
b0000001000 v
b1000011110 y
b0000000000 z
b0000001000 {
b1000011100 !"
b0000000000 ""
b0000001000 #"
b0111111011 &"
b0000000011 '"
1("
1-"
#320000000
0#
0)
08
0?
0D
0I
0N
0S
0X
0]
0b
0g
0l
0("
0-"
#340000000
1#
b0000001001 &
1)
b0000001001 ,
b0000001001 -
18
b0000001001 ;
b0000000011 <
b0000001010 =
b0000001001 >
1?
0B
1C
1D
1G
1I
1N
1S
1X
1]
1b
1g
1l
b0000001001 q
b1000101001 t
b0000000001 u
b0000001001 v
b1000011111 y
b0000011111 z
b0000001001 {
b1000011101 !"
b0000000001 ""
b0000001001 #"
b0111111010 &"
b0000000000 '"
1("
1-"
#360000000
0#
0)
08
0?
0D
0I
0N
0S
0X
0]
0b
0g
0l
0("
0-"
#380000000
1#
b0000001010 &
1)
b0000001010 ,
b0000001010 -
18
b0000001010 ;
b0000000001 <
b0000001011 =
b0000001010 >
1?
1B
0C
1D
1G
1H
1I
0L
1N
1S
1X
1]
1b
1g
1l
b0000001010 q
b1000101010 t
b0000000000 u
b0000001010 v
b1000011100 y
b0000000000 z
b0000001010 {
b1000011110 !"
b0000000000 ""
b0000001010 #"
b0111111001 &"
b0000000001 '"
1("
1-"
#400000000
0#
0)
08
0?
0D
0I
0N
0S
0X
0]
0b
0g
0l
0("
0-"
#420000000
1#
b0000001011 &
1)
b0000001011 ,
b0000001011 -
18
b0000001011 ;
b0000000111 <
b0000001100 =
b0000001011 >
1?
0B
1C
1D
0G
1I
1L
1N
1S
1X
1]
1b
1g
1l
b0000001011 q
b1000101011 t
b0000000011 u
b0000001011 v
b1000011101 y
b0000000001 z
b0000001011 {
b1000011111 !"
b0000011111 ""
b0000001011 #"
b0111111000 &"
b0000000000 '"
1("
1-"
#440000000
0#
0)
08
0?
0D
0I
0N
0S
0X
0]
0b
0g
0l
0("
0-"
#460000000
1#
b0000001100 &
1)
b0000001100 ,
b0000001100 -
18
b0000001100 ;
b0000000001 <
b0000001101 =
b0000001100 >
1?
1B
0C
1D
0G
0H
1I
1L
1M
1N
1Q
1S
0V
1X
1]
1b
1g
1l
b0000001100 q
b1000101100 t
b0000000000 u
b0000001100 v
b1000011010 y
b0000000000 z
b0000001100 {
b1000011000 !"
b0000000000 ""
b0000001100 #"
b0111111111 &"
b0111111111 '"
1("
1-"
#480000000
0#
0)
08
0?
0D
0I
0N
0S
0X
0]
0b
0g
0l
0("
0-"
#500000000
1#
b0000001101 &
1)
b0000001101 ,
b0000001101 -
18
b0000001101 ;
b0000000011 <
b0000001110 =
b0000001101 >
1?
0B
1C
1D
1G
1I
1N
1S
1X
1]
1b
1g
1l
b0000001101 q
b1000101101 t
b0000000001 u
b0000001101 v
b1000011011 y
b0000000011 z
b0000001101 {
b1000011001 !"
b0000000001 ""
b0000001101 #"
b0111111110 &"
b0000000000 '"
1("
1-"
#520000000
0#
0)
08
0?
0D
0I
0N
0S
0X
0]
0b
0g
0l
0("
0-"
#540000000
1#
b0000001110 &
1)
b0000001110 ,
b0000001110 -
18
b0000001110 ;
b0000000001 <
b0000001111 =
b0000001110 >
1?
1B
0C
1D
1G
1H
1I
1L
1N
1Q
1S
0V
1X
1]
1b
1g
1l
b0000001110 q
b1000101110 t
b0000000000 u
b0000001110 v
b1000011000 y
b0000000000 z
b0000001110 {
b1000011010 !"
b0000000000 ""
b0000001110 #"
b0111111101 &"
b0000000001 '"
1("
1-"
#560000000
0#
0)
08
0?
0D
0I
0N
0S
0X
0]
0b
0g
0l
0("
0-"
#580000000
1#
b0000001111 &
1)
b0000001111 ,
b0000001111 -
18
b0000001111 ;
b0000011111 <
b0000010000 =
b0000001111 >
1?
0B
1C
1D
0G
1I
0L
1N
0Q
1S
1V
1X
1]
1b
1g
1l
b0000001111 q
b1000101111 t
b0000001111 u
b0000001111 v
b1000011001 y
b0000000001 z
b0000001111 {
b1000011011 !"
b0000000011 ""
b0000001111 #"
b0111111100 &"
b0000000000 '"
1("
1-"
#600000000
0#
0)
08
0?
0D
0I
0N
0S
0X
0]
0b
0g
0l
0("
0-"
#620000000
1#
b0000010000 &
1)
b0000010000 ,
b0000010000 -
18
b0000010000 ;
b0000000001 <
b0000010001 =
b0000010000 >
1?
1B
0C
1D
0G
0H
1I
0L
0M
1N
0Q
0R
1S
1V
1W
1X
0[
1]
1b
1g
1l
b0000010000 q
b1000110000 t
b0000000000 u
b0000010000 v
b1000000110 y
b0000000000 z
b0000010000 {
b1000000100 !"
b0000000000 ""
b0000010000 #"
b0111100011 &"
b0000000011 '"
1("
1-"
#640000000
0#
0)
08
0?
0D
0I
0N
0S
0X
0]
0b
0g
0l
0("
0-"
#660000000
1#
b0000010001 &
1)
b0000010001 ,
b0000010001 -
18
b0000010001 ;
b0000000011 <
b0000010010 =
b0000010001 >
1?
0B
1C
1D
1G
1I
1N
1S
1X
1]
1b
1g
1l
b0000010001 q
b1000110001 t
b0000000001 u
b0000010001 v
b1000000111 y
b0000000111 z
b0000010001 {
b1000000101 !"
b0000000001 ""
b0000010001 #"
b0111100010 &"
b0000000000 '"
1("
1-"
#680000000
0#
0)
08
0?
0D
0I
0N
0S
0X
0]
0b
0g
0l
0("
0-"
#700000000
1#
b0000010010 &
1)
b0000010010 ,
b0000010010 -
18
b0000010010 ;
b0000000001 <
b0000010011 =
b0000010010 >
1?
1B
0C
1D
1G
1H
1I
0L
1N
1S
1X
1]
1b
1g
1l
b0000010010 q
b1000110010 t
b0000000000 u
b0000010010 v
b1000000100 y
b0000000000 z
b0000010010 {
b1000000110 !"
b0000000000 ""
b0000010010 #"
b0111100001 &"
b0000000001 '"
1("
1-"
#720000000
0#
0)
08
0?
0D
0I
0N
0S
0X
0]
0b
0g
0l
0("
0-"
#740000000
1#
b0000010011 &
1)
b0000010011 ,
b0000010011 -
18
b0000010011 ;
b0000000111 <
b0000010100 =
b0000010011 >
1?
0B
1C
1D
0G
1I
1L
1N
1S
1X
1]
1b
1g
1l
b0000010011 q
b1000110011 t
b0000000011 u
b0000010011 v
b1000000101 y
b0000000001 z
b0000010011 {
b1000000111 !"
b0000000111 ""
b0000010011 #"
b0111100000 &"
b0000000000 '"
1("
1-"
#760000000
0#
0)
08
0?
0D
0I
0N
0S
0X
0]
0b
0g
0l
0("
0-"
#780000000
1#
b0000010100 &
1)
b0000010100 ,
b0000010100 -
18
b0000010100 ;
b0000000001 <
b0000010101 =
b0000010100 >
1?
1B
0C
1D
0G
0H
1I
1L
1M
1N
0Q
1S
1X
1]
1b
1g
1l
b0000010100 q
b1000110100 t
b0000000000 u
b0000010100 v
b1000000010 y
b0000000000 z
b0000010100 {
b1000000000 !"
b0000000000 ""
b0000010100 #"
b0111100111 &"
b0000000111 '"
1("
1-"
#800000000
0#
0)
08
0?
0D
0I
0N
0S
0X
0]
0b
0g
0l
0("
0-"
#820000000
1#
b0000010101 &
1)
b0000010101 ,
b0000010101 -
18
b0000010101 ;
b0000000011 <
b0000010110 =
b0000010101 >
1?
0B
1C
1D
1G
1I
1N
1S
1X
1]
1b
1g
1l
b0000010101 q
b1000110101 t
b0000000001 u
b0000010101 v
b1000000011 y
b0000000011 z
b0000010101 {
b1000000001 !"
b0000000001 ""
b0000010101 #"
b0111100110 &"
b0000000000 '"
1("
1-"
#840000000
0#
0)
08
0?
0D
0I
0N
0S
0X
0]
0b
0g
0l
0("
0-"
#860000000
1#
b0000010110 &
1)
b0000010110 ,
b0000010110 -
18
b0000010110 ;
b0000000001 <
b0000010111 =
b0000010110 >
1?
1B
0C
1D
1G
1H
1I
1L
1N
0Q
1S
1X
1]
1b
1g
1l
b0000010110 q
b1000110110 t
b0000000000 u
b0000010110 v
b1000000000 y
b0000000000 z
b0000010110 {
b1000000010 !"
b0000000000 ""
b0000010110 #"
b0111100101 &"
b0000000001 '"
1("
1-"
#880000000
0#
0)
08
0?
0D
0I
0N
0S
0X
0]
0b
0g
0l
0("
0-"
#900000000
1#
b0000010111 &
1)
b0000010111 ,
b0000010111 -
18
b0000010111 ;
b0000001111 <
b0000011000 =
b0000010111 >
1?
0B
1C
1D
0G
1I
0L
1N
1Q
1S
1X
1]
1b
1g
1l
b0000010111 q
b1000110111 t
b0000000111 u
b0000010111 v
b1000000001 y
b0000000001 z
b0000010111 {
b1000000011 !"
b0000000011 ""
b0000010111 #"
b0111100100 &"
b0000000000 '"
1("
1-"
#920000000
0#
0)
08
0?
0D
0I
0N
0S
0X
0]
0b
0g
0l
0("
0-"
#940000000
1#
b0000011000 &
1)
b0000011000 ,
b0000011000 -
18
b0000011000 ;
b0000000001 <
b0000011001 =
b0000011000 >
1?
1B
0C
1D
0G
0H
1I
0L
0M
1N
1Q
1R
1S
1V
1X
0[
1]
1b
1g
1l
b0000011000 q
b1000111000 t
b0000000000 u
b0000011000 v
b1000001110 y
b0000000000 z
b0000011000 {
b1000001100 !"
b0000000000 ""
b0000011000 #"
b0111101011 &"
b0000000011 '"
1("
1-"
#960000000
0#
0)
08
0?
0D
0I
0N
0S
0X
0]
0b
0g
0l
0("
0-"
